[
  {
    "key": "en:ad-bio-154",
    "name": "AD-BIO-154"
  },
  {
    "key": "en:ae-bio-154",
    "name": "AE-BIO-154"
  },
  {
    "key": "en:af-bio-154",
    "name": "AF-BIO-154"
  },
  {
    "key": "en:al-bio-154",
    "name": "AL-BIO-154"
  },
  {
    "key": "en:am-bio-154",
    "name": "AM-BIO-154"
  },
  {
    "key": "en:ar-bio-154",
    "name": "AR-BIO-154"
  },
  {
    "key": "en:az-bio-154",
    "name": "AZ-BIO-154"
  },
  {
    "key": "en:ba-bio-154",
    "name": "BA-BIO-154"
  },
  {
    "key": "en:bd-bio-154",
    "name": "BD-BIO-154"
  },
  {
    "key": "en:bf-bio-154",
    "name": "BF-BIO-154"
  },
  {
    "key": "en:bh-bio-154",
    "name": "BH-BIO-154"
  },
  {
    "key": "en:bi-bio-154",
    "name": "BI-BIO-154"
  },
  {
    "key": "en:bj-bio-154",
    "name": "BJ-BIO-154"
  },
  {
    "key": "en:br-bio-154",
    "name": "BR-BIO-154"
  },
  {
    "key": "en:bs-bio-154",
    "name": "BS-BIO-154"
  },
  {
    "key": "en:bw-bio-154",
    "name": "BW-BIO-154"
  },
  {
    "key": "en:by-bio-154",
    "name": "BY-BIO-154"
  },
  {
    "key": "en:bz-bio-154",
    "name": "BZ-BIO-154"
  },
  {
    "key": "en:cd-bio-154",
    "name": "CD-BIO-154"
  },
  {
    "key": "en:cf-bio-154",
    "name": "CF-BIO-154"
  },
  {
    "key": "en:cg-bio-154",
    "name": "CG-BIO-154"
  },
  {
    "key": "en:ci-bio-154",
    "name": "CI-BIO-154"
  },
  {
    "key": "en:cl-bio-154",
    "name": "CL-BIO-154"
  },
  {
    "key": "en:cm-bio-154",
    "name": "CM-BIO-154"
  },
  {
    "key": "en:cn-bio-154",
    "name": "CN-BIO-154"
  },
  {
    "key": "en:co-bio-154",
    "name": "CO-BIO-154"
  },
  {
    "key": "en:cu-bio-154",
    "name": "CU-BIO-154"
  },
  {
    "key": "en:cv-bio-154",
    "name": "CV-BIO-154"
  },
  {
    "key": "en:do-bio-154",
    "name": "DO-BIO-154"
  },
  {
    "key": "en:dz-bio-154",
    "name": "DZ-BIO-154"
  },
  {
    "key": "en:ec-bio-154",
    "name": "EC-BIO-154"
  },
  {
    "key": "en:eg-bio-154",
    "name": "EG-BIO-154"
  },
  {
    "key": "en:et-bio-154",
    "name": "ET-BIO-154"
  },
  {
    "key": "en:fj-bio-154",
    "name": "FJ-BIO-154"
  },
  {
    "key": "en:ge-bio-154",
    "name": "GE-BIO-154"
  },
  {
    "key": "en:gh-bio-154",
    "name": "GH-BIO-154"
  },
  {
    "key": "en:gm-bio-154",
    "name": "GM-BIO-154"
  },
  {
    "key": "en:gn-bio-154",
    "name": "GN-BIO-154"
  },
  {
    "key": "en:gq-bio-154",
    "name": "GQ-BIO-154"
  },
  {
    "key": "en:gt-bio-154",
    "name": "GT-BIO-154"
  },
  {
    "key": "en:gw-bio-154",
    "name": "GW-BIO-154"
  },
  {
    "key": "en:gy-bio-154",
    "name": "GY-BIO-154"
  },
  {
    "key": "en:hk-bio-154",
    "name": "HK-BIO-154"
  },
  {
    "key": "en:hn-bio-154",
    "name": "HN-BIO-154"
  },
  {
    "key": "en:ht-bio-154",
    "name": "HT-BIO-154"
  },
  {
    "key": "en:id-bio-154",
    "name": "ID-BIO-154"
  },
  {
    "key": "en:in-bio-154",
    "name": "IN-BIO-154"
  },
  {
    "key": "en:ir-bio-154",
    "name": "IR-BIO-154"
  },
  {
    "key": "en:jo-bio-154",
    "name": "JO-BIO-154"
  },
  {
    "key": "en:jp-bio-154",
    "name": "JP-BIO-154"
  },
  {
    "key": "en:ke-bio-154",
    "name": "KE-BIO-154"
  },
  {
    "key": "en:kg-bio-154",
    "name": "KG-BIO-154"
  },
  {
    "key": "en:kh-bio-154",
    "name": "KH-BIO-154"
  },
  {
    "key": "en:km-bio-154",
    "name": "KM-BIO-154"
  },
  {
    "key": "en:kr-bio-154",
    "name": "KR-BIO-154"
  },
  {
    "key": "en:kw-bio-154",
    "name": "KW-BIO-154"
  },
  {
    "key": "en:kz-bio-154",
    "name": "KZ-BIO-154"
  },
  {
    "key": "en:la-bio-154",
    "name": "LA-BIO-154"
  },
  {
    "key": "en:lb-bio-154",
    "name": "LB-BIO-154"
  },
  {
    "key": "en:li-bio-154",
    "name": "LI-BIO-154"
  },
  {
    "key": "en:lk-bio-154",
    "name": "LK-BIO-154"
  },
  {
    "key": "en:lr-bio-154",
    "name": "LR-BIO-154"
  },
  {
    "key": "en:ls-bio-154",
    "name": "LS-BIO-154"
  },
  {
    "key": "en:ma-bio-154",
    "name": "MA-BIO-154"
  },
  {
    "key": "en:mc-bio-154",
    "name": "MC-BIO-154"
  },
  {
    "key": "en:md-bio-154",
    "name": "MD-BIO-154"
  },
  {
    "key": "en:me-bio-154",
    "name": "ME-BIO-154"
  },
  {
    "key": "en:mg-bio-154",
    "name": "MG-BIO-154"
  },
  {
    "key": "en:mk-bio-154",
    "name": "MK-BIO-154"
  },
  {
    "key": "en:ml-bio-154",
    "name": "ML-BIO-154"
  },
  {
    "key": "en:mm-bio-154",
    "name": "MM-BIO-154"
  },
  {
    "key": "en:mn-bio-154",
    "name": "MN-BIO-154"
  },
  {
    "key": "en:mr-bio-154",
    "name": "MR-BIO-154"
  },
  {
    "key": "en:mu-bio-154",
    "name": "MU-BIO-154"
  },
  {
    "key": "en:mw-bio-154",
    "name": "MW-BIO-154"
  },
  {
    "key": "en:mx-bio-154",
    "name": "MX-BIO-154"
  },
  {
    "key": "en:my-bio-154",
    "name": "MY-BIO-154"
  },
  {
    "key": "en:mz-bio-154",
    "name": "MZ-BIO-154"
  },
  {
    "key": "en:na-bio-154",
    "name": "NA-BIO-154"
  },
  {
    "key": "en:nc-bio-154",
    "name": "NC-BIO-154"
  },
  {
    "key": "en:ne-bio-154",
    "name": "NE-BIO-154"
  },
  {
    "key": "en:ng-bio-154",
    "name": "NG-BIO-154"
  },
  {
    "key": "en:ni-bio-154",
    "name": "NI-BIO-154"
  },
  {
    "key": "en:np-bio-154",
    "name": "NP-BIO-154"
  },
  {
    "key": "en:om-bio-154",
    "name": "OM-BIO-154"
  },
  {
    "key": "en:pa-bio-154",
    "name": "PA-BIO-154"
  },
  {
    "key": "en:pe-bio-154",
    "name": "PE-BIO-154"
  },
  {
    "key": "en:pf-bio-154",
    "name": "PF-BIO-154"
  },
  {
    "key": "en:ph-bio-154",
    "name": "PH-BIO-154"
  },
  {
    "key": "en:pk-bio-154",
    "name": "PK-BIO-154"
  },
  {
    "key": "en:ps-bio-154",
    "name": "PS-BIO-154"
  },
  {
    "key": "en:py-bio-154",
    "name": "PY-BIO-154"
  },
  {
    "key": "en:rs-bio-154",
    "name": "RS-BIO-154"
  },
  {
    "key": "en:ru-bio-154",
    "name": "RU-BIO-154"
  },
  {
    "key": "en:rw-bio-154",
    "name": "RW-BIO-154"
  },
  {
    "key": "en:sa-bio-154",
    "name": "SA-BIO-154"
  },
  {
    "key": "en:sc-bio-154",
    "name": "SC-BIO-154"
  },
  {
    "key": "en:sd-bio-154",
    "name": "SD-BIO-154"
  },
  {
    "key": "en:sg-bio-154",
    "name": "SG-BIO-154"
  },
  {
    "key": "en:sl-bio-154",
    "name": "SL-BIO-154"
  },
  {
    "key": "en:sn-bio-154",
    "name": "SN-BIO-154"
  },
  {
    "key": "en:so-bio-154",
    "name": "SO-BIO-154"
  },
  {
    "key": "en:sr-bio-154",
    "name": "SR-BIO-154"
  },
  {
    "key": "en:ss-bio-154",
    "name": "SS-BIO-154"
  },
  {
    "key": "en:st-bio-154",
    "name": "ST-BIO-154"
  },
  {
    "key": "en:sv-bio-154",
    "name": "SV-BIO-154"
  },
  {
    "key": "en:sy-bio-154",
    "name": "SY-BIO-154"
  },
  {
    "key": "en:sz-bio-154",
    "name": "SZ-BIO-154"
  },
  {
    "key": "en:td-bio-154",
    "name": "TD-BIO-154"
  },
  {
    "key": "en:tg-bio-154",
    "name": "TG-BIO-154"
  },
  {
    "key": "en:th-bio-154",
    "name": "TH-BIO-154"
  },
  {
    "key": "en:tj-bio-154",
    "name": "TJ-BIO-154"
  },
  {
    "key": "en:tl-bio-154",
    "name": "TL-BIO-154"
  },
  {
    "key": "en:tm-bio-154",
    "name": "TM-BIO-154"
  },
  {
    "key": "en:tn-bio-154",
    "name": "TN-BIO-154"
  },
  {
    "key": "en:tr-bio-154",
    "name": "TR-BIO-154"
  },
  {
    "key": "en:tw-bio-154",
    "name": "TW-BIO-154"
  },
  {
    "key": "en:tz-bio-154",
    "name": "TZ-BIO-154"
  },
  {
    "key": "en:ua-bio-154",
    "name": "UA-BIO-154"
  },
  {
    "key": "en:ug-bio-154",
    "name": "UG-BIO-154"
  },
  {
    "key": "en:uy-bio-154",
    "name": "UY-BIO-154"
  },
  {
    "key": "en:uz-bio-154",
    "name": "UZ-BIO-154"
  },
  {
    "key": "en:ve-bio-154",
    "name": "VE-BIO-154"
  },
  {
    "key": "en:vn-bio-154",
    "name": "VN-BIO-154"
  },
  {
    "key": "en:vu-bio-154",
    "name": "VU-BIO-154"
  },
  {
    "key": "en:ws-bio-154",
    "name": "WS-BIO-154"
  },
  {
    "key": "en:xk-bio-154",
    "name": "XK-BIO-154"
  },
  {
    "key": "en:za-bio-154",
    "name": "ZA-BIO-154"
  },
  {
    "key": "en:zm-bio-154",
    "name": "ZM-BIO-154"
  },
  {
    "key": "en:zw-bio-154",
    "name": "ZW-BIO-154"
  }
]