[
  {
    "key": "en:10-less-fat",
    "name": "10% less fat"
  },
  {
    "key": "en:15-less-fat",
    "name": "15% less fat"
  },
  {
    "key": "en:20-less-fat",
    "name": "20% less fat"
  },
  {
    "key": "en:25-less-fat",
    "name": "25% less fat"
  },
  {
    "key": "en:30-less-fat",
    "name": "30% less fat"
  },
  {
    "key": "en:35-less-fat",
    "name": "35% less fat"
  },
  {
    "key": "en:40-less-fat",
    "name": "40% less fat"
  },
  {
    "key": "en:45-less-fat",
    "name": "45% less fat"
  },
  {
    "key": "en:50-less-fat",
    "name": "50% less fat"
  },
  {
    "key": "en:55-less-fat",
    "name": "55% less fat"
  },
  {
    "key": "en:60-less-fat",
    "name": "60% less fat"
  },
  {
    "key": "en:65-less-fat",
    "name": "65% less fat"
  },
  {
    "key": "en:belgian-family-brewers",
    "name": "Belgian Family Brewers"
  },
  {
    "key": "en:fabrication",
    "name": "Fabrication"
  },
  {
    "key": "en:face",
    "name": "FACE"
  },
  {
    "key": "en:fair-for-life",
    "name": "Fair for Life"
  },
  {
    "key": "en:fair-trade",
    "name": "Fair trade"
  },
  {
    "key": "en:fair-trade-organic",
    "name": "Fair-Trade Organic"
  },
  {
    "key": "en:fairtrade-international",
    "name": "Fairtrade International"
  },
  {
    "key": "en:fairtrade-usa",
    "name": "Fairtrade USA"
  },
  {
    "key": "en:farm-verified-organic",
    "name": "Farm Verified Organic"
  },
  {
    "key": "en:high-level-of-fat-israel",
    "name": "High level of fat - Israel"
  },
  {
    "key": "en:incorrect-nutrition-facts-on-label",
    "name": "Incorrect nutrition facts on label"
  },
  {
    "key": "en:low-fat",
    "name": "Low fat"
  },
  {
    "key": "en:low-or-no-fat",
    "name": "Low or no fat"
  },
  {
    "key": "en:naturland-fair",
    "name": "Naturland Fair"
  },
  {
    "key": "en:no-added-fat",
    "name": "No added fat"
  },
  {
    "key": "en:no-fat",
    "name": "No fat"
  },
  {
    "key": "en:no-hydrogenated-fats",
    "name": "No hydrogenated fats"
  },
  {
    "key": "en:no-trans-fat",
    "name": "No Trans Fat"
  },
  {
    "key": "en:non-fair-trade",
    "name": "Non-fair trade"
  },
  {
    "key": "en:reduced-fat",
    "name": "Reduced fat"
  },
  {
    "key": "en:rich-in-polyunsaturated-fatty-acids",
    "name": "Rich in polyunsaturated fatty acids"
  },
  {
    "key": "en:sustainable-farming",
    "name": "Sustainable farming"
  }
]