[
  {
    "key": "en:trap-fishing",
    "name": "Angeln mit Fallen"
  },
  {
    "key": "en:belgian-family-brewers",
    "name": "Belgian Family Brewers"
  },
  {
    "key": "en:fabrication",
    "name": "Fabrication"
  },
  {
    "key": "en:face",
    "name": "FACE"
  },
  {
    "key": "en:fair-trade-organic",
    "name": "Fair-Trade Organic"
  },
  {
    "key": "en:fair-trade",
    "name": "Fairer Handel"
  },
  {
    "key": "en:fairtrade-international",
    "name": "Fairtrade International"
  },
  {
    "key": "en:incorrect-data-on-label",
    "name": "Falsche Angaben auf der Verpackung"
  },
  {
    "key": "en:incorrect-nutrition-facts-on-label",
    "name": "Falsche N채hrwertangaben auf dem Etikett"
  },
  {
    "key": "en:no-artificial-colours-or-flavours",
    "name": "Keine k체nstlichen Farbstoffe oder Aromen"
  },
  {
    "key": "en:natural-colorings",
    "name": "Nat체rliche Farbstoffe"
  },
  {
    "key": "en:without-dyes-or-preservatives",
    "name": "Ohne Farb- oder Konservierungsstoffe"
  },
  {
    "key": "en:no-colorings",
    "name": "Ohne Farbstoffzusatz"
  },
  {
    "key": "en:no-artificial-colors",
    "name": "Ohne k체nstliche Farbstoffe"
  }
]