[
  {
    "key": "en:low-density-polyethylene",
    "name": "Lagedichtheidpolyetheen"
  },
  {
    "key": "en:leaded-glass",
    "name": "Leaded Glass"
  },
  {
    "key": "en:light-leaded-glass",
    "name": "Light Leaded Glass"
  },
  {
    "key": "en:light-sort-glass",
    "name": "Light Sort Glass"
  },
  {
    "key": "en:lithium-battery",
    "name": "Lithium-ion-accu"
  },
  {
    "key": "en:lead-acid-battery",
    "name": "Lood"
  },
  {
    "key": "en:pak-lok",
    "name": "Pak-Lok"
  }
]