[
  {
    "key": "en:golden-delicious-apples",
    "name": "Golden Delicious appels"
  },
  {
    "key": "en:olive-oils-from-irpinia-colline-dell-ufita",
    "name": "Olijfoliën uit Irpinia - Colline dell'Ufita"
  },
  {
    "key": "en:olive-oils-from-pretuziano-delle-colline-teramane",
    "name": "Olijfoliën uit Pretuziano delle Colline Teramane"
  },
  {
    "key": "en:olive-oils-from-sierra-del-moncayo",
    "name": "Olijfoliën uit Sierra del Moncayo"
  },
  {
    "key": "en:olive-oils-from-valle-del-belice",
    "name": "Olijfoliën uit Valle del Belice"
  },
  {
    "key": "en:olive-oils-from-veneto-del-grappa",
    "name": "Olijfoliën uit Veneto del Grappa"
  },
  {
    "key": "en:poultry-sausage-delicatessen-style",
    "name": "Poultry sausage delicatessen style"
  },
  {
    "key": "en:red-delicious-apples",
    "name": "Red Delicious appels"
  },
  {
    "key": "en:turkish-delight",
    "name": "Turkish delight"
  },
  {
    "key": "nl:wijnen-uit-ambt-delden",
    "name": "Wijnen uit Ambt Delden"
  }
]