[
  {
    "key": "en:alcohol-vinegars",
    "name": "Alcohol vinegars"
  },
  {
    "key": "en:balsamic-vinegars",
    "name": "Balsamic vinegars"
  },
  {
    "key": "en:balsamic-vinegars-of-modena",
    "name": "Balsamic vinegars of Modena"
  },
  {
    "key": "en:black-rice-vinegars",
    "name": "Black rice vinegars"
  },
  {
    "key": "en:black-vinegars",
    "name": "Black vinegars"
  },
  {
    "key": "en:cider-vinegars",
    "name": "Cider vinegars"
  },
  {
    "key": "en:dorset-blue-vinney",
    "name": "Dorset Blue Vinney"
  },
  {
    "key": "en:glazes-with-balsamic-vinegar",
    "name": "Glazes with balsamic vinegar"
  },
  {
    "key": "en:glazes-with-vinegar",
    "name": "Glazes with vinegar"
  },
  {
    "key": "en:glazes-with-white-vinegar",
    "name": "Glazes with white vinegar"
  },
  {
    "key": "en:honey-vinegars",
    "name": "Honey vinegars"
  },
  {
    "key": "en:japanese-rice-vinegars",
    "name": "Japanese rice vinegars"
  },
  {
    "key": "en:red-rice-vinegars",
    "name": "Red rice vinegars"
  },
  {
    "key": "en:red-wine-vinegars",
    "name": "Red wine vinegars"
  },
  {
    "key": "en:rice-vinegars",
    "name": "Rice vinegars"
  },
  {
    "key": "en:rice-wine-vinegars",
    "name": "Rice wine vinegars"
  },
  {
    "key": "en:roscos-de-vino",
    "name": "Roscos de vino"
  },
  {
    "key": "en:salt-and-malt-vinegar-crisps",
    "name": "Salt and malt vinegar crisps"
  },
  {
    "key": "en:salt-and-vinegar-crisps",
    "name": "Salt and vinegar crisps"
  },
  {
    "key": "en:spanish-vinegars",
    "name": "Spanish vinegars"
  },
  {
    "key": "en:stuffed-vine-leaves",
    "name": "Stuffed vine leaves"
  },
  {
    "key": "en:sugarcane-vinegars",
    "name": "Sugarcane vinegars"
  },
  {
    "key": "en:tomato-vinegars",
    "name": "Tomato vinegars"
  },
  {
    "key": "en:traditional-balsamic-vinegar-of-modena",
    "name": "Traditional Balsamic Vinegar of Modena"
  },
  {
    "key": "en:traditional-balsamic-vinegar-of-reggio-emilia",
    "name": "Traditional Balsamic Vinegar of Reggio Emilia"
  },
  {
    "key": "en:traditional-balsamic-vinegars",
    "name": "Traditional Balsamic Vinegars"
  },
  {
    "key": "en:umeboshi-vinegars",
    "name": "Umeboshi vinegars"
  },
  {
    "key": "en:vinaigrettes",
    "name": "Vinaigrettes"
  },
  {
    "key": "en:vinegars",
    "name": "Vinegars"
  },
  {
    "key": "en:white-rice-vinegars",
    "name": "White rice vinegars"
  },
  {
    "key": "en:white-vinegars",
    "name": "White vinegars"
  },
  {
    "key": "en:white-wine-vinegars",
    "name": "White wine vinegars"
  },
  {
    "key": "en:wine-vinegars",
    "name": "Wine vinegars"
  },
  {
    "key": "en:xeres-vinegars",
    "name": "Xeres vinegars"
  }
]