[
  {
    "key": "en:daikon-radishes",
    "name": "Daikon radishes"
  },
  {
    "key": "en:dairy-chocolate-desserts",
    "name": "Dairy chocolate desserts"
  },
  {
    "key": "en:dairy-mousses",
    "name": "Dairy Mousses"
  },
  {
    "key": "en:dark-maple-syrups",
    "name": "Dark maple syrups"
  },
  {
    "key": "en:darnitsky-bread",
    "name": "Darnitsky bread"
  },
  {
    "key": "en:date-syrups",
    "name": "Date syrups"
  },
  {
    "key": "en:dates",
    "name": "Datteln"
  },
  {
    "key": "en:lollipops",
    "name": "Dauerlutscher"
  },
  {
    "key": "fr:damassine",
    "name": "Eau de Damassine"
  },
  {
    "key": "en:pitted-dates",
    "name": "Entkernte Datteln"
  },
  {
    "key": "en:whole-dates",
    "name": "Ganze Datteln"
  },
  {
    "key": "en:hams-of-san-daniele",
    "name": "Hams of San Daniele"
  }
]