[
  {
    "key": "en:boiled-kohlrabi",
    "name": "Boiled kohlrabi"
  },
  {
    "key": "en:cabbages",
    "name": "Kohl"
  },
  {
    "key": "en:canned-cabbage",
    "name": "Kohl in Dosen"
  },
  {
    "key": "en:carbonated-drinks",
    "name": "Kohlensäurehaltige Getränke"
  },
  {
    "key": "en:kohlrabi",
    "name": "Kohlrabi"
  },
  {
    "key": "en:carbonated-mineral-waters",
    "name": "Mineralwasser mit Kohlensäure"
  },
  {
    "key": "en:carbonated-natural-mineral-waters",
    "name": "Natürliches Mineralwasser mit Kohlensäure versetzt"
  },
  {
    "key": "en:mildly-carbonated-natural-mineral-water",
    "name": "Natürliches Mineralwasser mit wenig Kohlensäure versetzt"
  },
  {
    "key": "en:non-carbonated-natural-mineral-waters",
    "name": "Natürliches Mineralwasser ohne Kohlensäure"
  }
]