[
  {
    "key": "en:fresh-mixed-vegetables",
    "name": "Frische Gemüse Mischung"
  },
  {
    "key": "en:mixed-vegetables",
    "name": "Gemüse Mischung"
  },
  {
    "key": "en:honey-and-royal-jelly-mixtures",
    "name": "Honig und Gelée Royale Mischungen"
  },
  {
    "key": "en:blends-of-honey-and-propolis",
    "name": "Honig und Propolis Mischungen"
  },
  {
    "key": "de:mischfette",
    "name": "Mischfette"
  },
  {
    "key": "en:mixed-drinks",
    "name": "Mischgetränk"
  },
  {
    "key": "de:mischstreichfett",
    "name": "Mischstreichfett"
  },
  {
    "key": "en:falafel-mixes",
    "name": "Mischung für Falafel"
  },
  {
    "key": "en:miso-soup",
    "name": "Miso-Suppe"
  },
  {
    "key": "en:misos",
    "name": "Misos"
  },
  {
    "key": "en:medlars",
    "name": "Mispeln"
  }
]