[
  {
    "key": "en:apple-pulp",
    "name": "Apple pulp"
  },
  {
    "key": "en:apple-pulp-and-peel",
    "name": "Apple pulp and peel"
  },
  {
    "key": "en:avocado-pulp",
    "name": "Avocado pulp"
  },
  {
    "key": "en:banana-pulp",
    "name": "Banana pulp"
  },
  {
    "key": "en:boiled-tomato-pulp-and-peel",
    "name": "Boiled tomato pulp and peel"
  },
  {
    "key": "en:canada-apple-pulp",
    "name": "Canada apple pulp"
  },
  {
    "key": "en:canned-tomato-pulp",
    "name": "Canned tomato pulp"
  },
  {
    "key": "en:cantaloupe-melon-pulp",
    "name": "Cantaloupe melon pulp"
  },
  {
    "key": "en:clementine-pulp",
    "name": "Clementine pulp"
  },
  {
    "key": "en:cooked-pulp-and-peel-courgette",
    "name": "Cooked pulp and peel courgette"
  },
  {
    "key": "en:cooked-pulses",
    "name": "Cooked pulses"
  },
  {
    "key": "en:cooked-spaghetti-squash-pulp",
    "name": "Cooked spaghetti squash pulp"
  },
  {
    "key": "en:courgette-pulp-and-peel",
    "name": "Courgette pulp and peel"
  },
  {
    "key": "en:curry-powder",
    "name": "Curry Pulver"
  },
  {
    "key": "en:dried-date-pulp-and-peel",
    "name": "Dried date pulp and peel"
  },
  {
    "key": "en:frozen-courgette-pulp-and-peel",
    "name": "Frozen courgette pulp and peel"
  },
  {
    "key": "en:golden-apple-pulp-and-skin",
    "name": "Golden apple pulp and skin"
  },
  {
    "key": "en:grapefruit-pulp",
    "name": "Grapefruit pulp"
  },
  {
    "key": "en:guava-pulp",
    "name": "Guava pulp"
  },
  {
    "key": "en:honeydew-melon-pulp",
    "name": "Honeydew melon pulp"
  },
  {
    "key": "en:immature-tamarind-pulp",
    "name": "Immature tamarind pulp"
  },
  {
    "key": "en:kiwi-fruit-pulp-and-seeds",
    "name": "Kiwi fruit pulp and seeds"
  },
  {
    "key": "en:turmeric-powder",
    "name": "Kurkuma Pulver"
  },
  {
    "key": "en:lemon-pulp",
    "name": "Lemon pulp"
  },
  {
    "key": "en:lime-pulp",
    "name": "Lime pulp"
  },
  {
    "key": "en:lychee-pulp",
    "name": "Lychee pulp"
  },
  {
    "key": "en:mandarin-pulp",
    "name": "Mandarin pulp"
  },
  {
    "key": "en:mango-pulp",
    "name": "Mango pulp"
  },
  {
    "key": "en:nectarine-pulp-and-peel",
    "name": "Nectarine pulp and peel"
  },
  {
    "key": "en:orange-pulp",
    "name": "Orange pulp"
  },
  {
    "key": "en:papaya-pulp",
    "name": "Papaya pulp"
  },
  {
    "key": "en:passion-fruit-pulp-and-pips",
    "name": "Passion fruit pulp and pips"
  },
  {
    "key": "en:peach-pulp-and-peel",
    "name": "Peach pulp and peel"
  },
  {
    "key": "en:pear-pulp-and-peel",
    "name": "Pear pulp and peel"
  },
  {
    "key": "en:persimmon-pulp",
    "name": "Persimmon pulp"
  },
  {
    "key": "en:pineapple-pulp",
    "name": "Pineapple pulp"
  },
  {
    "key": "en:pomegranate-pulp-and-pips",
    "name": "Pomegranate pulp and pips"
  },
  {
    "key": "en:puffed-pulse-cakes",
    "name": "Puffed pulse cakes"
  },
  {
    "key": "en:pulp-of-melonnette-jaspee-from-vendee",
    "name": "Pulp of melonnette jaspée from Vendée"
  },
  {
    "key": "en:pummelo-pulp",
    "name": "Pummelo pulp"
  },
  {
    "key": "en:pumpkin-pulp",
    "name": "Pumpkin pulp"
  },
  {
    "key": "en:red-grapefruit-pulp",
    "name": "Red grapefruit pulp"
  },
  {
    "key": "en:roasted-apple-pulp",
    "name": "Roasted apple pulp"
  },
  {
    "key": "en:spaghetti-squash-pulp",
    "name": "Spaghetti squash pulp"
  },
  {
    "key": "en:squash-pulp",
    "name": "Squash pulp"
  },
  {
    "key": "en:tomato-pulps",
    "name": "Tomato pulps"
  },
  {
    "key": "en:watermelon-pulp",
    "name": "Watermelon pulp"
  },
  {
    "key": "en:yellow-grapefruit-pulp",
    "name": "Yellow grapefruit pulp"
  }
]