[
  {
    "key": "en:tunisian-eaux-de-vie",
    "name": "Branntwein aus Tunesien"
  },
  {
    "key": "en:breaded-turkey",
    "name": "Breaded turkey"
  },
  {
    "key": "en:christmas-turkeys",
    "name": "Christmas Turkeys"
  },
  {
    "key": "en:nougat-ice-cream-tubs",
    "name": "Nougat ice cream tubs"
  },
  {
    "key": "en:pistachio-ice-cream-tubs",
    "name": "Pistachio ice cream tubs"
  },
  {
    "key": "en:plant-based-ice-cream-tubs",
    "name": "Plant-based ice cream tubs"
  },
  {
    "key": "en:rum-and-raisins-ice-cream-tubs",
    "name": "Rum and raisins ice cream tubs"
  },
  {
    "key": "en:smoked-tunas",
    "name": "Smoked tunas"
  },
  {
    "key": "en:strawberry-ice-cream-tubs",
    "name": "Strawberry ice cream tubs"
  },
  {
    "key": "en:toasted-egg-yolk-turron",
    "name": "Toasted egg yolk turrón"
  },
  {
    "key": "en:tula-gingerbread",
    "name": "Tula-Lebkuchen"
  },
  {
    "key": "en:tumacas",
    "name": "Tumacas"
  },
  {
    "key": "en:tuna-chunks",
    "name": "Tuna chunks"
  },
  {
    "key": "en:tuna-lasagna",
    "name": "Tuna lasagna"
  },
  {
    "key": "en:tuna-pies",
    "name": "Tuna pies"
  },
  {
    "key": "en:tuna-rillettes",
    "name": "Tuna rillettes"
  },
  {
    "key": "en:tuna-samosas",
    "name": "Tuna samosas"
  },
  {
    "key": "en:tuna-sandwiches",
    "name": "Tuna sandwiches"
  },
  {
    "key": "en:tuna-sushis",
    "name": "Tuna sushis"
  },
  {
    "key": "en:turkey-breasts",
    "name": "Turkey breasts"
  },
  {
    "key": "en:turkey-dishes",
    "name": "Turkey dishes"
  },
  {
    "key": "en:turkey-fillets",
    "name": "Turkey fillets"
  },
  {
    "key": "en:turkey-nuggets",
    "name": "Turkey nuggets"
  },
  {
    "key": "en:turkey-rillettes",
    "name": "Turkey rillettes"
  },
  {
    "key": "en:turkey-sandwiches",
    "name": "Turkey sandwiches"
  },
  {
    "key": "en:turkey-thighs",
    "name": "Turkey thighs"
  },
  {
    "key": "en:turmeric",
    "name": "Turmeric"
  },
  {
    "key": "en:turmeric-powder",
    "name": "Turmeric powder"
  },
  {
    "key": "en:turmeric-rhizomes",
    "name": "Turmeric rhizomes"
  },
  {
    "key": "en:turron",
    "name": "Turrón"
  },
  {
    "key": "en:guirlache-turron",
    "name": "Turron de Guirlache"
  },
  {
    "key": "en:walnut-creme-turron",
    "name": "Walnut creme turrón"
  },
  {
    "key": "en:whole-tunas",
    "name": "Whole tunas"
  }
]