[
  {
    "key": "en:bananas",
    "name": "Bananes"
  },
  {
    "key": "en:gummy-bananas",
    "name": "Bananes gélifiées"
  },
  {
    "key": "en:plantain-bananas",
    "name": "Bananes plantains"
  },
  {
    "key": "en:red-banana",
    "name": "Bananes rouges"
  },
  {
    "key": "en:dried-bananas",
    "name": "Bananes séchées"
  },
  {
    "key": "en:banderillas",
    "name": "Banderillas"
  },
  {
    "key": "fr:bandol",
    "name": "Bandol"
  },
  {
    "key": "en:banh-bao",
    "name": "Banh Bao (Pain brioché farci)"
  },
  {
    "key": "fr:banon",
    "name": "Banon"
  },
  {
    "key": "fr:banyuls",
    "name": "Banyuls"
  },
  {
    "key": "en:banana-cereal-bars",
    "name": "Barres de céréales à la banane"
  },
  {
    "key": "fr:compotes-pommes-banane",
    "name": "Compotes pommes banane"
  },
  {
    "key": "en:banana-jams",
    "name": "Confitures de bananes"
  },
  {
    "key": "en:banana-muffins",
    "name": "Muffins à la banane"
  },
  {
    "key": "en:banana-nectars",
    "name": "Nectars de banane"
  },
  {
    "key": "fr:piment-banane",
    "name": "Piment banane"
  },
  {
    "key": "en:bancha-teas",
    "name": "Thés bancha"
  },
  {
    "key": "en:banana-yogurts",
    "name": "Yaourts à la banane"
  },
  {
    "key": "en:banana-soy-yogurts",
    "name": "Yaourts de soja à la banane"
  }
]