[
  {
    "key": "en:roasted-chicken-wing-meat-and-skin",
    "name": "Aile de poulet avec viande et peau rôtie"
  },
  {
    "key": "en:roasted-eel",
    "name": "Anguille rôtie"
  },
  {
    "key": "en:roasted-european-bass",
    "name": "Bar commun rôti"
  },
  {
    "key": "fr:blancs-de-poulet-roti-a-la-broche",
    "name": "Blancs de poulet rôti à la broche"
  },
  {
    "key": "en:roasted-beef-bolar-blade",
    "name": "Boule de macreuse de boeuf rôtie"
  },
  {
    "key": "en:roasted-northern-pike",
    "name": "Brochet rôti"
  },
  {
    "key": "en:roasted-cods",
    "name": "Cabillauds rôtis"
  },
  {
    "key": "en:roasted-duck-with-meat-and-skin",
    "name": "Canard rôti avec viande et peau"
  },
  {
    "key": "fr:carpe-rotie",
    "name": "Carpe rôtie"
  },
  {
    "key": "en:roasted-hart",
    "name": "Cerf rôti"
  },
  {
    "key": "en:baked-capon-meat-and-skin",
    "name": "Chapon rôti avec viande et peau"
  },
  {
    "key": "en:roasted-venison",
    "name": "Chevreuil rôti"
  },
  {
    "key": "fr:cote-rotie",
    "name": "Côte Rôtie"
  },
  {
    "key": "en:roasted-chicken-leg-meat-and-skin",
    "name": "Cuisse de poulet rôtie avec viande et peau"
  },
  {
    "key": "en:roasted-chicken-leg-meat",
    "name": "Cuisse de poulet rôtie sans peau"
  },
  {
    "key": "en:roasted-black-seabream",
    "name": "Dorade grise rôtie"
  },
  {
    "key": "fr:echine-de-porc-rotie",
    "name": "Échine de porc rôtie"
  },
  {
    "key": "en:roasted-lean-lamb-shoulders",
    "name": "Epaules d'agneau maigres rôties"
  },
  {
    "key": "en:roasted-lamb-shoulders",
    "name": "Epaules rôties d'agneau"
  },
  {
    "key": "en:roasted-turkey-escalope",
    "name": "Escalope de dinde rôtie"
  },
  {
    "key": "en:roasted-swordfish",
    "name": "Espadon rôti"
  },
  {
    "key": "en:roasted-beef-sirloin-steak",
    "name": "Faux-filet de boeuf rôti"
  },
  {
    "key": "en:roasted-horse-sirloin-steak",
    "name": "Faux-filet de cheval rôti"
  },
  {
    "key": "en:pork-eye-of-shortloin",
    "name": "Filet de porc rôti avec chaînette"
  },
  {
    "key": "en:cooked-pork-tenderloin-roast",
    "name": "Filet maigre de porc en rôti cuit"
  },
  {
    "key": "fr:filets-de-poulet-rotis",
    "name": "Filets de poulet rotis"
  },
  {
    "key": "en:roasted-veal-fillet",
    "name": "Filets de veau rôtis"
  },
  {
    "key": "en:roasted-lamb-leg",
    "name": "Gigot d'agneau rôti au four"
  },
  {
    "key": "en:roasted-mackerel",
    "name": "Maquereau rôti"
  },
  {
    "key": "fr:morey-saint-denis-premier-cru-cote-rotie",
    "name": "Morey-Saint-Denis premier cru Côte Rotie"
  },
  {
    "key": "fr:morey-saint-denis-premier-cru-cote-rotie-blanc",
    "name": "Morey-Saint-Denis premier cru Côte Rotie blanc"
  },
  {
    "key": "fr:morey-saint-denis-premier-cru-cote-rotie-rouge",
    "name": "Morey-Saint-Denis premier cru Côte Rotie rouge"
  },
  {
    "key": "en:roasted-mullet",
    "name": "Mulet rôti"
  },
  {
    "key": "en:roasted-veal-tenderloin",
    "name": "Noix de veau rôtie"
  },
  {
    "key": "en:roasted-goose-with-meat-and-skin",
    "name": "Oie rôtie avec viande et peau"
  },
  {
    "key": "en:roasted-european-perch",
    "name": "Perche rôtie"
  },
  {
    "key": "en:roasted-chicken-breast-with-meat-and-skin",
    "name": "Poitrine de poulet rôtie avec viande et peau"
  },
  {
    "key": "en:roasted-potatoes",
    "name": "Pommes de terre rôties"
  },
  {
    "key": "en:roast-chicken",
    "name": "Poulets rôtis"
  },
  {
    "key": "en:roasted-apple-pulp",
    "name": "Pulpe de pomme rôtie"
  },
  {
    "key": "en:roasted-tomato-with-skin",
    "name": "Pulpe et peau de tomate rôtie"
  },
  {
    "key": "en:roasted-ray",
    "name": "Raie rôtie"
  },
  {
    "key": "fr:rillettes-de-poulet-roti",
    "name": "Rillettes de poulet rôti"
  },
  {
    "key": "en:roast-beef",
    "name": "Rosbif rôti"
  },
  {
    "key": "en:cooked-pork-roast",
    "name": "Rôti de porc cuit"
  },
  {
    "key": "en:cooked-veal-roast",
    "name": "Rôti de veau cuit"
  },
  {
    "key": "en:cooked-curing-salted-roast-poultry",
    "name": "Rôti de volaille en salaison cuit"
  },
  {
    "key": "en:roasted-turkey-meat",
    "name": "Rôtis de dinde"
  },
  {
    "key": "en:pork-roasts",
    "name": "Rôtis de porc"
  },
  {
    "key": "en:roast-veal",
    "name": "Rôtis de veau"
  },
  {
    "key": "en:roasted-wild-boar",
    "name": "Sanglier rôti"
  },
  {
    "key": "en:roasted-lean-lamb-saddle",
    "name": "Selle d'agneau partie maigre rôtie"
  },
  {
    "key": "en:roasted-common-sole",
    "name": "Sole rôtie"
  },
  {
    "key": "en:roasted-horse-topside",
    "name": "Tende de cheval rôtie"
  },
  {
    "key": "en:roasted-beef-topside",
    "name": "Tende de tranche de boeuf rôtie"
  },
  {
    "key": "en:roasted-tuna",
    "name": "Thon rôti"
  },
  {
    "key": "en:roasted-rainbow-trout-from-farming",
    "name": "Truite arc en ciel d'élevage rôtie"
  },
  {
    "key": "en:roasted-trout",
    "name": "Truite rôtie"
  },
  {
    "key": "en:roasted-turbot",
    "name": "Turbot rôti"
  },
  {
    "key": "en:roasted-goose-meat",
    "name": "Viande d'oie rôtie"
  },
  {
    "key": "en:roasted-duck-meat",
    "name": "Viande de canard rôtie"
  },
  {
    "key": "en:roasted-horse-meat",
    "name": "Viande de cheval rôtie"
  },
  {
    "key": "en:roasted-pheasant-meat",
    "name": "Viande de faisan rôtie"
  },
  {
    "key": "en:roasted-pigeon-meat",
    "name": "Viande de pigeon rôtie"
  }
]