[
  {
    "key": "en:dried-soy-beans",
    "name": "Dried soy beans"
  },
  {
    "key": "en:flavoured-soy-drinks-enriched-in-calcium-with-sugar",
    "name": "Flavoured soy drinks enriched in calcium with sugar"
  },
  {
    "key": "en:plain-soy-drink-fortified-with-calcium",
    "name": "Plain soy drink fortified with calcium"
  },
  {
    "key": "en:puffed-salty-snacks-made-from-potato-and-soy",
    "name": "Puffed salty snacks made from potato and soy"
  },
  {
    "key": "en:soy-drinks-flavoured-with-sugar",
    "name": "Soy drinks flavoured with sugar"
  },
  {
    "key": "en:soy-based-minced-prepacked",
    "name": "Soy-based minced prepacked"
  },
  {
    "key": "en:soy-based-patty-plain-vegetable-steak-prepacked",
    "name": "Soy-based patty plain (vegetable steak) prepacked"
  },
  {
    "key": "en:uht-soy-based-drinks",
    "name": "UHT soy based drinks"
  }
]