[
  {
    "key": "en:2-3-fat-petit-suisse-fruits-flavoured-fortified-with-calcium-and-vitamin-d",
    "name": "2-3% fat Petit-Suisse fruits flavoured fortified with calcium and vitamin D"
  },
  {
    "key": "en:almond-flakes",
    "name": "Almond flakes"
  },
  {
    "key": "en:baguette-made-with-type-t55-t110-flour",
    "name": "Baguette made with type T55-T110 flour"
  },
  {
    "key": "en:banana-flours",
    "name": "Banana flours"
  },
  {
    "key": "en:beef-flank-steak",
    "name": "Beef flank steak"
  },
  {
    "key": "en:beef-thin-flank",
    "name": "Beef thin flank"
  },
  {
    "key": "en:bergamot-flavored-black-teas",
    "name": "Bergamot flavored black teas"
  },
  {
    "key": "en:bircher-style-muesli-flakes-with-fruits-fortified-with-vitamins-and-chemical-elements",
    "name": "Bircher-style muesli flakes with fruits fortified with vitamins and chemical elements"
  },
  {
    "key": "en:bircher-style-muesli-flakes-with-fruits-not-fortified-with-vitamins-and-chemical-elements",
    "name": "Bircher-style muesli flakes with fruits not fortified with vitamins and chemical elements"
  },
  {
    "key": "en:bircher-style-sugar-free-muesli-flakes-with-fruits",
    "name": "Bircher-style sugar free muesli flakes with fruits"
  }
]