[
  {
    "key": "en:2-3-fat-petit-suisse-fruits-flavoured-fortified-with-calcium-and-vitamin-d",
    "name": "2-3% fat Petit-Suisse fruits flavoured fortified with calcium and vitamin D"
  },
  {
    "key": "en:2-3-fat-petit-suisse-with-fruits-fortified-with-calcium-and-vitamin-d",
    "name": "2-3% fat Petit-Suisse with fruits fortified with calcium and vitamin D"
  },
  {
    "key": "en:olive-oils-from-campo-de-calatrava",
    "name": "Aceite Campo de Calatrava"
  },
  {
    "key": "en:pumpkin-seed-oils",
    "name": "Aceites de semillas de calabaza"
  },
  {
    "key": "en:hot-beverages",
    "name": "Bebidas para tomar calientes"
  },
  {
    "key": "en:boiled-calf-head",
    "name": "Boiled calf head"
  },
  {
    "key": "en:fresh-zucchini",
    "name": "Calabacín fresco"
  },
  {
    "key": "en:zucchini",
    "name": "Calabacines"
  },
  {
    "key": "en:frozen-zucchini",
    "name": "Calabacines congelados"
  },
  {
    "key": "en:frozen-diced-zucchinis",
    "name": "Calabacines en dados congelados"
  },
  {
    "key": "en:frozen-sliced-zucchini",
    "name": "Calabacines en rodajas congelados"
  },
  {
    "key": "en:pumpkins",
    "name": "Calabazas"
  },
  {
    "key": "en:butternut-squashes",
    "name": "Calabazas Butternut"
  },
  {
    "key": "en:frozen-pumpkins",
    "name": "Calabazas congeladas"
  },
  {
    "key": "en:spaghetti-squashes",
    "name": "Calabazas espagueti"
  },
  {
    "key": "en:pumpkins-and-their-products",
    "name": "Calabazas y derivados"
  },
  {
    "key": "en:calamari",
    "name": "Calamares"
  },
  {
    "key": "es:calasparra",
    "name": "Calasparra"
  },
  {
    "key": "es:calatayud",
    "name": "Calatayud"
  },
  {
    "key": "es:calcot-de-valls",
    "name": "Calçot de Valls"
  },
  {
    "key": "en:broths",
    "name": "Caldos"
  },
  {
    "key": "en:vegetable-broths",
    "name": "Caldos de verduras"
  },
  {
    "key": "en:dehydrated-vegetable-bouillons",
    "name": "Caldos de verduras deshidratados"
  },
  {
    "key": "en:vegetable-bouillon-pots",
    "name": "Caldos de verduras en cacitos"
  },
  {
    "key": "en:vegetable-bouillon-cubes",
    "name": "Caldos de verduras en cubitos"
  },
  {
    "key": "en:vegetable-bouillon-powders",
    "name": "Caldos de verduras en polvo"
  },
  {
    "key": "en:liquid-vegetable-bouillons",
    "name": "Caldos de verduras líquidos"
  },
  {
    "key": "en:dehydrated-broths",
    "name": "Caldos deshidratados"
  },
  {
    "key": "en:bouillon-pots",
    "name": "Caldos en cacitos"
  },
  {
    "key": "en:bouillon-cubes",
    "name": "Caldos en cubitos"
  },
  {
    "key": "en:bouillon-powders",
    "name": "Caldos en polvo"
  },
  {
    "key": "en:liquid-broths",
    "name": "Caldos líquidos"
  },
  {
    "key": "en:advent-calendars",
    "name": "Calendarios de Adviento"
  },
  {
    "key": "en:calf-brain",
    "name": "Calf brain"
  },
  {
    "key": "en:calf-foot",
    "name": "Calf foot"
  },
  {
    "key": "en:calf-kidney",
    "name": "Calf kidney"
  },
  {
    "key": "en:calf-liver",
    "name": "Calf liver"
  },
  {
    "key": "en:calf-sweetbread",
    "name": "Calf sweetbread"
  },
  {
    "key": "en:calf-tongue",
    "name": "Calf tongue"
  },
  {
    "key": "en:californian-makis",
    "name": "Californian makis"
  },
  {
    "key": "en:calissons",
    "name": "Calissons"
  },
  {
    "key": "en:calissons-d-aix",
    "name": "Calissons d'Aix"
  },
  {
    "key": "en:tripe",
    "name": "Callos"
  },
  {
    "key": "en:calvados",
    "name": "Calvados"
  },
  {
    "key": "es:calzadilla",
    "name": "Calzadilla"
  },
  {
    "key": "en:camembert-with-calvados",
    "name": "Camembert con Calvados"
  },
  {
    "key": "en:chocolate-advent-calendars",
    "name": "Chocolate Advent calendars"
  },
  {
    "key": "es:coliflor-de-calahorra",
    "name": "Coliflor de Calahorra"
  },
  {
    "key": "en:confectioneries-of-nord-pas-de-calais",
    "name": "Confectioneries of Nord-Pas-de-Calais"
  },
  {
    "key": "en:cooked-calf-brain",
    "name": "Cooked calf brain"
  },
  {
    "key": "en:cooked-calf-liver",
    "name": "Cooked calf liver"
  },
  {
    "key": "en:cooked-calf-tongue",
    "name": "Cooked calf tongue"
  },
  {
    "key": "en:cream-of-zucchini-soups",
    "name": "Cremas de calabacines"
  },
  {
    "key": "en:cream-of-pumpkin-soups",
    "name": "Cremas de calabaza"
  },
  {
    "key": "en:flavoured-soy-drinks-enriched-in-calcium-with-sugar",
    "name": "Flavoured soy drinks enriched in calcium with sugar"
  },
  {
    "key": "en:low-calorie-cereal-bar",
    "name": "Low calorie cereal bar"
  },
  {
    "key": "en:low-calorie-custard-cream-meal-replacement",
    "name": "Low calorie custard cream meal replacement"
  },
  {
    "key": "en:low-calorie-meal-replacement",
    "name": "Low calorie meal replacement"
  },
  {
    "key": "en:low-calorie-meal-replacement-in-powder-reconstituted-with-skimmed-milk",
    "name": "Low calorie meal replacement in powder reconstituted with skimmed milk"
  },
  {
    "key": "en:low-calorie-milkshake-meal-replacement-in-powder-reconstituted-with-skimmed-milk",
    "name": "Low calorie milkshake meal replacement in powder reconstituted with skimmed milk"
  },
  {
    "key": "en:low-calorie-ready-to-drink-meal-replacement",
    "name": "Low calorie ready-to-drink meal replacement"
  },
  {
    "key": "en:pumpkin-seed-butters",
    "name": "Mantecas de semilla de calabaza"
  },
  {
    "key": "es:melocoton-de-calanda",
    "name": "Melocotón de Calanda"
  },
  {
    "key": "en:pumpkin-jams",
    "name": "Mermeladas y confituras de calabaza"
  },
  {
    "key": "en:mixtures-of-vegetables-for-broth",
    "name": "Mezclas de verduras y hortalizas para caldo"
  },
  {
    "key": "es:nisperos-callosa-d-en-sarria",
    "name": "Nísperos Callosa d'En Sarriá"
  },
  {
    "key": "en:olive-oils-from-olio-di-calabria",
    "name": "Olive oils from Olio di Calabria"
  },
  {
    "key": "en:pan-fried-calf-sweetbread",
    "name": "Pan-fried calf sweetbread"
  },
  {
    "key": "en:hot-dog-buns",
    "name": "Panecillos para perritos calientes"
  },
  {
    "key": "en:hot-dog-sandwiches",
    "name": "Perritos calientes"
  },
  {
    "key": "en:vegetarian-hot-dog-sandwiches",
    "name": "Perritos calientes vegetales"
  },
  {
    "key": "en:petit-suisse-fortified-with-calcium-and-vitamin-d",
    "name": "Petit-Suisse fortified with calcium and vitamin D"
  },
  {
    "key": "en:plain-soy-drink-fortified-with-calcium",
    "name": "Plain soy drink fortified with calcium"
  },
  {
    "key": "en:pumpkin-and-squash-plant-products",
    "name": "Productos de la planta de la calabaza"
  },
  {
    "key": "en:vegetarian-hot-dog-sausages",
    "name": "Salchichas vegetales para perritos calientes"
  },
  {
    "key": "en:pumpkin-seeds",
    "name": "Semillas de calabaza"
  },
  {
    "key": "en:unshelled-pumpkin-seeds",
    "name": "Semillas de calabaza con cáscara"
  },
  {
    "key": "en:roasted-unshelled-pumpkin-seeds",
    "name": "Semillas de calabaza con cáscara tostadas"
  },
  {
    "key": "en:shelled-pumpkin-seeds",
    "name": "Semillas de calabaza sin cáscara"
  },
  {
    "key": "en:roasted-shelled-pumpkin-seeds",
    "name": "Semillas de calabaza sin cáscara tostadas"
  },
  {
    "key": "en:roasted-pumpkin-seeds",
    "name": "Semillas de calabaza tostadas"
  },
  {
    "key": "en:pumpkin-seeds-and-their-products",
    "name": "Semillas de calabaza y derivados"
  },
  {
    "key": "en:zucchini-soups",
    "name": "Sopas De Calabacín"
  },
  {
    "key": "en:wines-from-california",
    "name": "Wines from California"
  }
]