[
  {
    "key": "en:30-40-fat-lightly-salted-vegetable-fat",
    "name": "30-40% fat lightly salted vegetable fat"
  },
  {
    "key": "en:30-40-lightly-salted-blended-fat-with-vegetable-and-animal-origins",
    "name": "30-40% lightly salted blended fat with vegetable and animal origins"
  },
  {
    "key": "en:30-40-lightly-salted-vegetable-fat-with-plant-sterols-esters",
    "name": "30-40% lightly salted vegetable fat with plant sterols esters"
  },
  {
    "key": "en:50-63-fat-lightly-salted-vegetable-fat",
    "name": "50-63% fat lightly salted vegetable fat"
  },
  {
    "key": "en:50-63-lightly-salted-blended-fat-with-vegetable-and-animal-origins",
    "name": "50-63% lightly salted blended fat with vegetable and animal origins"
  },
  {
    "key": "en:50-63-lightly-salted-vegetable-fat-high-in-omega-3",
    "name": "50-63% lightly salted vegetable fat high in omega 3"
  },
  {
    "key": "en:diet-cola-soft-drink",
    "name": "Bebida de cola light"
  },
  {
    "key": "en:diet-beverages",
    "name": "Bebidas light"
  },
  {
    "key": "en:canned-apricots-in-light-syrup-not-drained",
    "name": "Canned apricots in light syrup not drained"
  },
  {
    "key": "en:canned-drained-apricots-in-light-syrup",
    "name": "Canned drained apricots in light syrup"
  },
  {
    "key": "en:canned-drained-fruit-cocktail-in-light-syrup",
    "name": "Canned drained fruit cocktail in light syrup"
  },
  {
    "key": "en:canned-drained-peach-in-light-syrup",
    "name": "Canned drained peach in light syrup"
  },
  {
    "key": "en:canned-drained-pineapple-in-light-syrup",
    "name": "Canned drained pineapple in light syrup"
  },
  {
    "key": "en:canned-fruit-cocktail-in-light-syrup",
    "name": "Canned fruit cocktail in light syrup"
  },
  {
    "key": "en:canned-peach-in-light-syrup",
    "name": "Canned peach in light syrup"
  },
  {
    "key": "en:canned-pineapple-in-light-syrup-not-drained",
    "name": "Canned pineapple in light syrup not drained"
  },
  {
    "key": "en:light-compotes",
    "name": "Compotas ligeras"
  },
  {
    "key": "en:dairy-fat-20-fat-light-spreadable-unsalted",
    "name": "Dairy fat 20% fat light spreadable unsalted"
  },
  {
    "key": "en:dairy-fat-25-fat-light-spreadable-unsalted",
    "name": "Dairy fat 25% fat light spreadable unsalted"
  },
  {
    "key": "en:extra-light-maple-syrups",
    "name": "Extra light maple syrups"
  },
  {
    "key": "en:light-butter",
    "name": "Light butter"
  },
  {
    "key": "en:light-cheese-buche-from-goat-s-milk",
    "name": "Light cheese buche from goat's milk"
  },
  {
    "key": "en:light-couscous-with-meat",
    "name": "Light couscous with meat"
  },
  {
    "key": "en:light-custard-cream-with-vanilla",
    "name": "Light custard cream with vanilla"
  },
  {
    "key": "en:light-fruit-sodas",
    "name": "Light fruit sodas"
  },
  {
    "key": "en:light-lemon-soft-drinks",
    "name": "Light lemon soft drinks"
  },
  {
    "key": "en:light-maple-syrups",
    "name": "Light maple syrups"
  },
  {
    "key": "en:light-orange-soft-drinks",
    "name": "Light orange soft drinks"
  },
  {
    "key": "en:light-potato-crisps",
    "name": "Light potato crisps"
  },
  {
    "key": "en:light-sugar-with-aspartame",
    "name": "Light sugar with aspartame"
  },
  {
    "key": "en:light-syrup-for-canned-fruits",
    "name": "Light syrup for canned fruits"
  },
  {
    "key": "en:light-unsalted-butter-with-60-62-fat",
    "name": "Light unsalted butter with 60-62% fat"
  },
  {
    "key": "en:light-unsalted-margarines",
    "name": "Light unsalted margarines"
  },
  {
    "key": "en:lightly-salted-butter-with-80-fat",
    "name": "Lightly salted butter with 80% fat"
  },
  {
    "key": "en:lightly-salted-light-butter-with-60-62-fat",
    "name": "Lightly salted light butter with 60-62% fat"
  },
  {
    "key": "en:liquid-15-20-fat-light-cream-uht",
    "name": "Liquid 15-20% fat light cream UHT"
  },
  {
    "key": "en:liquid-light-cream-with-4-to-8-fat",
    "name": "Liquid light cream with 4 to 8% fat"
  },
  {
    "key": "en:light-margarines",
    "name": "Margarinas ligeras"
  },
  {
    "key": "en:light-mayonnaises",
    "name": "Mayonesas ligeras"
  },
  {
    "key": "en:low-sugar-fruit-jam",
    "name": "Mermeladas y confituras ligeras"
  },
  {
    "key": "en:olive-oils-from-riviera-ligure",
    "name": "Olive oils from Riviera Ligure"
  },
  {
    "key": "en:refrigerated-15-20-fat-light-thick-cream",
    "name": "Refrigerated 15-20% fat light thick cream"
  },
  {
    "key": "en:diet-sodas",
    "name": "Sodas light"
  },
  {
    "key": "en:light-iced-teas",
    "name": "Tés helados ligeros"
  },
  {
    "key": "en:extruded-crispbreads",
    "name": "Tostadas ligeras crujientes"
  },
  {
    "key": "en:unsalted-light-butter-with-39-41-fat",
    "name": "Unsalted light butter with 39-41% fat"
  }
]