[
  {
    "key": "en:30-40-fat-unsalted-vegetable-fat-high-in-omega-3",
    "name": "30-40% fat unsalted vegetable fat high in omega 3"
  },
  {
    "key": "en:50-63-lightly-salted-vegetable-fat-high-in-omega-3",
    "name": "50-63% lightly salted vegetable fat high in omega 3"
  },
  {
    "key": "en:50-63-unsalted-vegetable-fat-high-in-omega-3",
    "name": "50-63% unsalted vegetable fat high in omega 3"
  },
  {
    "key": "en:herb-omelette",
    "name": "Herb omelette"
  },
  {
    "key": "en:margarines-high-in-omega-3",
    "name": "Margarines high in omega 3"
  },
  {
    "key": "en:omelette-with-lardoons",
    "name": "Omelette with lardoons"
  },
  {
    "key": "en:omelette-with-meat",
    "name": "Omelette with meat"
  },
  {
    "key": "en:omelette-with-mushrooms",
    "name": "Omelette with mushrooms"
  },
  {
    "key": "en:omelette-with-vegetables",
    "name": "Omelette with vegetables"
  },
  {
    "key": "en:omelettes-with-cheese",
    "name": "Omelettes with cheese"
  }
]