[
  {
    "key": "es:jamon-de-seron",
    "name": "Jamón de Serón"
  },
  {
    "key": "en:serrano-ham",
    "name": "Jamón Serrano"
  },
  {
    "key": "en:dried-products-to-be-rehydrated",
    "name": "Productos deshidratados para ser rehidratados"
  },
  {
    "key": "es:queso-de-la-serena",
    "name": "Queso de La Serena"
  },
  {
    "key": "en:serbian-wines",
    "name": "Serbian wines"
  },
  {
    "key": "es:serra-de-tramuntana-costa-nord",
    "name": "Serra de Tramuntana-Costa Nord"
  }
]