[
  {
    "key": "en:acacia-honeys-from-alsace",
    "name": "Acacia honeys from Alsace"
  },
  {
    "key": "en:acacia-honeys-from-jura",
    "name": "Acacia honeys from Jura"
  },
  {
    "key": "en:agave-syrups",
    "name": "Agavensäfte"
  },
  {
    "key": "en:almond-flakes",
    "name": "Almond flakes"
  },
  {
    "key": "en:squeezed-pineapple-juices",
    "name": "Ananasdirektsäfte"
  },
  {
    "key": "en:pineapple-juices",
    "name": "Ananassäfte"
  },
  {
    "key": "en:concentrated-pineapple-juices",
    "name": "Ananassäfte aus Konzentrat"
  },
  {
    "key": "en:pineapple-juice-and-soy-drinks",
    "name": "Annanasssäfte und Sojagetränke"
  },
  {
    "key": "en:squeezed-apple-juices",
    "name": "Apfeldirektsäfte"
  },
  {
    "key": "en:concentrated-apple-juices",
    "name": "Apfelsäfte aus Konzentrat"
  }
]