[
  {
    "key": "en:australian-international-beer-awards",
    "name": "Australian International Beer Awards"
  },
  {
    "key": "en:authentic-trappist-product",
    "name": "Authentic Trappist Product"
  },
  {
    "key": "en:bio-austria",
    "name": "Bio Austria"
  },
  {
    "key": "en:australian-made",
    "name": "Fabricado en Australia"
  },
  {
    "key": "en:halal-food-authority",
    "name": "Halal Food Authority"
  },
  {
    "key": "en:sephardi-kashrut-autority",
    "name": "Sephardi Kashrut Autority"
  }
]