[
  {
    "key": "en:angled-fish",
    "name": "Angled fish"
  },
  {
    "key": "en:assured-food-standards",
    "name": "Assured Food Standards"
  },
  {
    "key": "en:bee-friendly",
    "name": "Bee Friendly"
  },
  {
    "key": "en:belgian-family-brewers",
    "name": "Belgian Family Brewers"
  },
  {
    "key": "en:blast-fished",
    "name": "Blast fished"
  },
  {
    "key": "en:qualite-france-french-quality",
    "name": "Calidad francesa"
  },
  {
    "key": "en:french-meat",
    "name": "Carne francesa"
  },
  {
    "key": "en:french-pork",
    "name": "Cerdo frances"
  },
  {
    "key": "en:certified-gluten-free",
    "name": "Certified gluten-free"
  },
  {
    "key": "en:cooked-in-france",
    "name": "Cocinado en francia"
  }
]